flask_assets_pipeline/__init__.py
flask_assets_pipeline/builders/__init__.py
flask_assets_pipeline/builders/base.py
flask_assets_pipeline/builders/cache-worker.js
flask_assets_pipeline/builders/cache_worker.py
flask_assets_pipeline/builders/esbuild.py
flask_assets_pipeline/builders/node_deps.py
flask_assets_pipeline/builders/static.py
flask_assets_pipeline/builders/tailwind.py
flask_assets_pipeline/builders/templates.py
flask_assets_pipeline/cli.py
flask_assets_pipeline/esbuild.mjs
flask_assets_pipeline/ext.py
flask_assets_pipeline/file_processors/__init__.py
flask_assets_pipeline/file_processors/external.py
flask_assets_pipeline/file_processors/image.py
flask_assets_pipeline/image.py
flask_assets_pipeline/jinja.py
flask_assets_pipeline/livereload.py
flask_assets_pipeline-0.8.0.dist-info/WHEEL
flask_assets_pipeline-0.8.0.dist-info/METADATA
flask_assets_pipeline-0.8.0.dist-info/RECORD
