Metadata-Version: 2.4
Name: flask-assets-pipeline
Version: 0.8.0
Summary: Modern asset pipeline for Flask
Author: Maxime Bouroumeau-Fuseau
Author-email: Maxime Bouroumeau-Fuseau <maxime.bouroumeau@gmail.com>
License-Expression: MIT
Requires-Dist: flask~=3.0
Requires-Dist: watchdog~=6.0
Requires-Python: >=3.10
Project-URL: Repository, https://github.com/hyperflask/flask-assets-pipeline
